benfordslaw_analysis/__init__.py
benfordslaw_analysis/analysis.py
benfordslaw_analysis-1.1.0.dist-info/METADATA
benfordslaw_analysis-1.1.0.dist-info/WHEEL
benfordslaw_analysis-1.1.0.dist-info/top_level.txt
benfordslaw_analysis-1.1.0.dist-info/RECORD
